FbBirthday
