Metadata-Version: 1.0
Name: BirthdayFb
Version: 0.3
Summary: Schedule your Birthday wishes for your facebook friends and never Miss any birthdays
Home-page: https://github.com/ankitpyc/Autopy/tree/master/Facebook_BirthdayWish_/Fb_Birthday
Author: Ankit Mishra
Author-email: ankitmishra@gmail.com
License: MIT
Platform: UNKNOWN
